{
    "carros": [
        {
            "marca": "Mazda",
            "modelo": "6",
            "color":"Rojo",
            "combustible":"Gasolina",
            "ano":"2013",
            "direccion":"Hidráulica",
            "aireacon":"Si",
            "asientos":"Tela",
            "vidrios":"Si",
            "espejoslat":"Eléctricos",
            "sonido":"mp3",
            "imaUno": "",
            "imaDos": "",
            "imaTres": "",
            "imaCuatro": "",
            "imaCinco": "",
            "imaSeis": "",
            "fichatec":"",
            "desc_corta":"",
            "desc_larga":""
        }
        ,
        {
            "marca": "Mazda",
            "modelo": "6",
            "color":"Rojo",
            "combustible":"Gasolina",
            "ano":"2013",
            "direccion":"Hidráulica",
            "aireacon":"Si",
            "asientos":"Tela",
            "vidrios":"Si",
            "espejoslat":"Eléctricos",
            "sonido":"mp3",
            "imaUno": "",
            "imaDos": "",
            "imaTres": "",
            "imaCuatro": "",
            "imaCinco": "",
            "imaSeis": "",
            "fichatec":"",
            "desc_corta":"",
            "desc_larga":""
        },{
            "marca": "Mazda",
            "modelo": "6",
            "color":"Rojo",
            "combustible":"Gasolina",
            "ano":"2013",
            "direccion":"Hidráulica",
            "aireacon":"Si",
            "asientos":"Tela",
            "vidrios":"Si",
            "espejoslat":"Eléctricos",
            "sonido":"mp3",
            "imaUno": "",
            "imaDos": "",
            "imaTres": "",
            "imaCuatro": "",
            "imaCinco": "",
            "imaSeis": "",
            "fichatec":"",
            "desc_corta":"",
            "desc_larga":""
        },{
            "marca": "Mazda",
            "modelo": "6",
            "color":"Rojo",
            "combustible":"Gasolina",
            "ano":"2013",
            "direccion":"Hidráulica",
            "aireacon":"Si",
            "asientos":"Tela",
            "vidrios":"Si",
            "espejoslat":"Eléctricos",
            "sonido":"mp3",
            "imaUno": "",
            "imaDos": "",
            "imaTres": "",
            "imaCuatro": "",
            "imaCinco": "",
            "imaSeis": "",
            "fichatec":"",
            "desc_corta":"",
            "desc_larga":""
        }
]
}